ahri_api/__init__.py
Ahri_API-1.0.dist-info/METADATA
Ahri_API-1.0.dist-info/WHEEL
Ahri_API-1.0.dist-info/top_level.txt
Ahri_API-1.0.dist-info/RECORD
